kaa/_version.py
kaa/log.py
kaa/__init__.py
kaa/physics.py
kaa/engine.py
kaa/cli.py
kaa/transitions.py
kaa/input.py
kaa/_bin.py
kaa/geometry.py
kaa/images.py
kaa/audio.py
kaa/statistics.py
kaa/nodes.py
kaa/timers.py
kaa/sprites.py
kaa/fonts.py
kaa/_kaa.cpython-37m-darwin.so
kaa/easings.py
kaa/colors.py
kaa/tools/__init__.py
kaa/tools/stats_graph.py
kaa/bin/shaderc
kaa/.dylibs/libSDL2-2.0.dylib
kaaengine-0.11.dist-info/RECORD
kaaengine-0.11.dist-info/LICENSE
kaaengine-0.11.dist-info/WHEEL
kaaengine-0.11.dist-info/entry_points.txt
kaaengine-0.11.dist-info/top_level.txt
kaaengine-0.11.dist-info/METADATA
